area_of_shapes_by_code_with_ishraq/__init__.py
area_of_shapes_by_code_with_ishraq/areas.py
area_of_shapes_by_code_with_ishraq-0.0.1.dist-info/METADATA
area_of_shapes_by_code_with_ishraq-0.0.1.dist-info/WHEEL
area_of_shapes_by_code_with_ishraq-0.0.1.dist-info/top_level.txt
area_of_shapes_by_code_with_ishraq-0.0.1.dist-info/RECORD
