Metadata-Version: 2.1
Name: area-of-shapes-by-code-with-ishraq
Version: 0.0.1
Summary: Area of different shapes
Home-page: UNKNOWN
Author: Ishraq Haider Chowdhury
Author-email: ishraq.h.c@gmail.com
License: UNKNOWN
Platform: UNKNOWN
